[
  {
    "date": "2022-03-12",
    "title": "Ambassadors to Sri Lanka Stand #UnitedwithUkraine",
    "source": "island.lk",
    "snippet": "Issuing a press release the United States Embassy said 17 Ambassadors and High Commissioners to Sri Lanka gathered in Colombo on Friday to stand together as an expression of their solidarity with and concern for Ukraine.",
    "url": "https://island.lk/ambassadors-to-sri-lanka-stand-unitedwithukraine/",
    "url_hash": "4e1e435dfb3c272bb57b784273398edb",
    "ut": 1647043396,
    "ent_info_list": [
      {
        "label": "ORG",
        "text": "the United States Embassy",
        "start_end": [
          4,
          8
        ]
      },
      {
        "label": "CARDINAL",
        "text": "17",
        "start_end": [
          9,
          10
        ]
      },
      {
        "label": "GPE",
        "text": "Sri Lanka",
        "start_end": [
          15,
          17
        ]
      },
      {
        "label": "GPE",
        "text": "Colombo",
        "start_end": [
          19,
          20
        ]
      },
      {
        "label": "DATE",
        "text": "Friday",
        "start_end": [
          21,
          22
        ]
      },
      {
        "label": "GPE",
        "text": "Ukraine",
        "start_end": [
          35,
          36
        ]
      }
    ]
  },
  {
    "date": "2022-03-12",
    "title": "Sri Lanka told to rest Chameera",
    "source": "island.lk",
    "snippet": "Rex Clementine in Bangalore Captain Dimuth Karunaratne must be an angry man after being told to rest his pace ace Dushmantha Chameera from today's second Test match against India here at the Chinnaswamy Stadium in Bangalore.",
    "url": "https://island.lk/sri-lanka-told-to-rest-chameera/",
    "url_hash": "ddf27d4790a9b56d2614b7aab96962b2",
    "ut": 1647043576,
    "ent_info_list": [
      {
        "label": "PERSON",
        "text": "Rex Clementine",
        "start_end": [
          0,
          2
        ]
      },
      {
        "label": "PERSON",
        "text": "Bangalore",
        "start_end": [
          3,
          4
        ]
      },
      {
        "label": "PERSON",
        "text": "Dimuth Karunaratne",
        "start_end": [
          5,
          7
        ]
      },
      {
        "label": "PERSON",
        "text": "Dushmantha Chameera",
        "start_end": [
          20,
          22
        ]
      },
      {
        "label": "DATE",
        "text": "today",
        "start_end": [
          23,
          24
        ]
      },
      {
        "label": "ORDINAL",
        "text": "second",
        "start_end": [
          25,
          26
        ]
      },
      {
        "label": "GPE",
        "text": "India",
        "start_end": [
          29,
          30
        ]
      },
      {
        "label": "FAC",
        "text": "the Chinnaswamy Stadium",
        "start_end": [
          32,
          35
        ]
      },
      {
        "label": "PERSON",
        "text": "Bangalore",
        "start_end": [
          36,
          37
        ]
      }
    ]
  },
  {
    "date": "2022-03-12",
    "title": "Tackling land forgery in Sri Lanka",
    "source": "www.msn.com",
    "snippet": "As land forgery continues unabated in Sri Lanka, something has to be done to prevent the prevalent rate of land fraud, with legal owners and innocent buyers unknowingly falling into these traps.According to news sources,",
    "url": "https://www.msn.com/en-xl/asia/srilanka/tackling-land-forgery-in-sri-lanka/ar-AAUXJiw",
    "url_hash": "3cba6647caf3913da45791b900db9d8b",
    "ut": 1647044467,
    "ent_info_list": [
      {
        "label": "GPE",
        "text": "Sri Lanka",
        "start_end": [
          6,
          8
        ]
      }
    ]
  },
  {
    "date": "2022-03-12",
    "title": "RBI operationalises US$ 500 mn loan provided to Sri Lanka for petro items",
    "source": "www.msn.com",
    "snippet": "Mumbai: The Reserve Bank of India (RBI) on Thursday issued a notification to operationalise the US$ 500-million Line of Credit provided by India to Sri Lanka, to buy petroleum products.The Export-Import Bank of India (Exim Bank) entered into a pact on February 2,",
    "url": "https://www.msn.com/en-xl/asia/srilanka/rbi-operationalises-us-500-mn-loan-provided-to-sri-lanka-for-petro-items/ar-AAUXtpq",
    "url_hash": "289bdebb693c0873a378fd88f509788e",
    "ut": 1647044467,
    "ent_info_list": [
      {
        "label": "GPE",
        "text": "Mumbai",
        "start_end": [
          0,
          1
        ]
      },
      {
        "label": "ORG",
        "text": "The Reserve Bank of India",
        "start_end": [
          2,
          7
        ]
      },
      {
        "label": "ORG",
        "text": "RBI",
        "start_end": [
          8,
          9
        ]
      },
      {
        "label": "DATE",
        "text": "Thursday",
        "start_end": [
          11,
          12
        ]
      },
      {
        "label": "MONEY",
        "text": "US$ 500-million",
        "start_end": [
          18,
          22
        ]
      },
      {
        "label": "GPE",
        "text": "India",
        "start_end": [
          27,
          28
        ]
      },
      {
        "label": "GPE",
        "text": "Sri Lanka",
        "start_end": [
          29,
          31
        ]
      },
      {
        "label": "ORG",
        "text": "The Export-Import Bank of India",
        "start_end": [
          37,
          44
        ]
      },
      {
        "label": "DATE",
        "text": "February 2",
        "start_end": [
          53,
          55
        ]
      }
    ]
  },
  {
    "date": "2022-03-12",
    "title": "Sri Lanka to start talks with IMF as economic crisis worsens \u2014 sources",
    "source": "www.malaymail.com",
    "snippet": "Sri Lanka will begin talks with the International Monetary Fund (IMF) next month on a plan to help the crisis-hit country, where a foreign exchange shortage has squeezed essential imports amid looming debt payments,",
    "url": "https://www.malaymail.com/news/money/2022/03/12/sri-lanka-to-start-talks-with-imf-as-economic-crisis-worsens-sources/2046972",
    "url_hash": "1d1b5da9d461d93859821a9177699f12",
    "ut": 1647048067,
    "ent_info_list": [
      {
        "label": "GPE",
        "text": "Sri Lanka",
        "start_end": [
          0,
          2
        ]
      },
      {
        "label": "ORG",
        "text": "the International Monetary Fund",
        "start_end": [
          6,
          10
        ]
      },
      {
        "label": "DATE",
        "text": "next month",
        "start_end": [
          13,
          15
        ]
      }
    ]
  }
]