[
  {
    "date": "2021-08-01",
    "title": "Buddhism is India's most precious gift to Sri Lanka",
    "source": "island.lk",
    "snippet": "Milinda Moragoda urges Special Relationship with India BY S VENKAT NARAYAN Our Special Correspondent NEW DELHI, July 30: Sri Lanka's High Commissioner-designate to India Milinda Moragoda says Buddhism is India's \"most precious gift\" to the island nation,",
    "url": "http://island.lk/buddhism-is-indias-most-precious-gift-to-sri-lanka/",
    "url_hash": "243072381fbed570a2ab45f755b35580",
    "ut": 1627776216,
    "ent_info_list": [
      {
        "label": "PERSON",
        "text": "Milinda Moragoda",
        "start_end": [
          0,
          2
        ]
      },
      {
        "label": "GPE",
        "text": "India",
        "start_end": [
          6,
          7
        ]
      },
      {
        "label": "DATE",
        "text": "July 30",
        "start_end": [
          17,
          19
        ]
      },
      {
        "label": "GPE",
        "text": "Sri Lanka's",
        "start_end": [
          20,
          23
        ]
      },
      {
        "label": "GPE",
        "text": "India",
        "start_end": [
          28,
          29
        ]
      },
      {
        "label": "PERSON",
        "text": "Milinda Moragoda",
        "start_end": [
          29,
          31
        ]
      },
      {
        "label": "GPE",
        "text": "India",
        "start_end": [
          34,
          35
        ]
      }
    ]
  },
  {
    "date": "2021-08-01",
    "title": "Sri Lanka Magic Circle to celebrate its centenary in 2022",
    "source": "island.lk",
    "snippet": "The Sri Lanka Magic Circle has rendered a great service over the years by nurturing magicians and improving their skills by conducting training workshops and magic contests, Prime Minister Mahinda Rajapaksa said in a congratulatory message to mark its centenary celebrations on February 18,",
    "url": "http://island.lk/sri-lanka-magic-circle-to-celebrate-its-centenary-in-2022/",
    "url_hash": "aa6d43701a535d75de6512403baeaabf",
    "ut": 1627776156,
    "ent_info_list": [
      {
        "label": "DATE",
        "text": "the years",
        "start_end": [
          11,
          13
        ]
      },
      {
        "label": "PERSON",
        "text": "Mahinda Rajapaksa",
        "start_end": [
          30,
          32
        ]
      },
      {
        "label": "DATE",
        "text": "February 18",
        "start_end": [
          43,
          45
        ]
      }
    ]
  },
  {
    "date": "2021-08-01",
    "title": "Oman shows interest in SLAF HQ land and Chalmer's Granary",
    "source": "www.sundaytimes.lk",
    "snippet": "An Omani Government investment arm has shown initial interest in the property on which the Air Force Headquarters is situated in Colombo 2 and the Urban Development Authority-owned Chalmer's Granary land in Colombo Fort,",
    "url": "https://www.sundaytimes.lk/210801/news/oman-shows-interest-in-slaf-hq-land-and-chalmers-granary-451258.html",
    "url_hash": "f69aefaed7139748aa1435b4adc25b01",
    "ut": 1627776649,
    "ent_info_list": [
      {
        "label": "ORG",
        "text": "the Air Force Headquarters",
        "start_end": [
          14,
          18
        ]
      },
      {
        "label": "ORG",
        "text": "the Urban Development Authority",
        "start_end": [
          24,
          28
        ]
      },
      {
        "label": "ORG",
        "text": "Chalmer's Granary",
        "start_end": [
          30,
          33
        ]
      },
      {
        "label": "GPE",
        "text": "Colombo Fort",
        "start_end": [
          35,
          37
        ]
      }
    ]
  }
]