{
  "--- 2021-08-03-0601 ---": null,
  "AFP": null,
  "AIC Campus": null,
  "Abu Dhabi": "🇦🇪#AbuDhabi",
  "Accel Partners": null,
  "Ada Derana": null,
  "Afghan": "🇦🇫#Afghan",
  "Afghan Embassy": null,
  "Afghanistan": "🇦🇫#Afghanistan",
  "Air Force Headquarters": null,
  "Airbus": null,
  "Ajith Rohana": "#Ajith Rohana",
  "Akira Sugiyama": "#AkiraSugiyama",
  "Alaina": null,
  "Alaina B. Teplitz": null,
  "Ali Sabry": null,
  "All-India Senior Selection Committee": null,
  "Alliance to End Plastic Waste": "@EndPlasticWaste",
  "Alumni Association of the University of Colombo": "Alumni Association @ColomboUni",
  "America": "#America",
  "Amir Sheikh": null,
  "Amrit Mohotsav'": null,
  "Angampora": "#Angampora",
  "Angampora Martial Arts Show": null,
  "Angelo Mathews": "@Angelo69Mathews",
  "Anna": null,
  "Antton Pena": null,
  "Anwar A. Khan": null,
  "Aralaganwila": "#Aralaganwila",
  "Argentinian": "🇦🇷#Argentinian",
  "Ariz.": null,
  "Army": null,
  "Army Commander's League": null,
  "Army Media Unit": null,
  "Aroshi Nanayakkara": null,
  "Ashish Nehra": "@NehraJi",
  "Ashraf Haidari": "@MAshrafHaidari",
  "Asian": null,
  "Asian Banking & Finance Retail Banking Awards": null,
  "Assam": "#Assam",
  "Assam-Mizoram": "#AssamMizoram",
  "Association of Professional Bankers": null,
  "Astra": null,
  "AstraZeneca": "#AstraZeneca",
  "Australia": "🇦🇺#Australia",
  "Azad Kashmir": null,
  "AztraZeneca": "#AstraZeneca",
  "B. Teplitz": null,
  "BBC": "@BBC",
  "BCCI": "@BCCI",
  "BJP": "@BJP4India",
  "BOI": "@BOIsrilanka",
  "Badulla": "#Badulla",
  "Bairaha Farms PLC": "@BairahaP",
  "Bandaranaike International Airport": "#BandaranaikeInternationalAirport",
  "Bangalore": "#Bangalore",
  "Bangladesh": "🇧🇩#Bangladesh",
  "Baroda": null,
  "Basil Rajapaksa": null,
  "BeachTech Hydro": null,
  "Beijing": null,
  "Belihuloya": null,
  "Ben Stokes": null,
  "Best Small Businesses'": null,
  "Biden": null,
  "Big Cat": null,
  "Bill": null,
  "Bloemendhal, Colombo": null,
  "Board of Control for Cricket": null,
  "Board of Governors": null,
  "Board of Investment": null,
  "Bollywood": null,
  "Bologna": null,
  "Bope, Padukka": null,
  "Britain": null,
  "Browns": null,
  "Browns Group": null,
  "Browns and Makita": null,
  "CARSON CITY": null,
  "CDB": null,
  "CMC": null,
  "COO": null,
  "CSE": null,
  "Carlo Scarpa": null,
  "Catholic": null,
  "Catholic Bishops Conference": null,
  "Centers for Disease Control and Prevention": null,
  "Central Colombo Toastmasters Club": null,
  "Ceylon Chamber of Commerce": null,
  "Ceylon Electricity Board": null,
  "Ceylon Teachers'": null,
  "Chalmer's Granary": null,
  "Chamber Academy": null,
  "Chamika Karunaratne": null,
  "Channa Jayasumana": null,
  "Channel Islands": null,
  "Chathura Supun": null,
  "Chilaw": null,
  "China": null,
  "Chinese": null,
  "Chinese National Defence University": null,
  "Chronic Kidney Disease (CKD": null,
  "Citizens Development Business Finance": null,
  "Colo": null,
  "Colombo": null,
  "Colombo Fort": null,
  "Colombo Municipal Council": null,
  "Commercial Bank of Ceylon": null,
  "Commission of Inquiry": null,
  "Commonwealth Centre": null,
  "Conglomerates Expolanka Holdings": null,
  "Copernicus": null,
  "Coronavirus": null,
  "Court": null,
  "Covid": null,
  "Creative Software": null,
  "Cricbuzz": null,
  "DIG": null,
  "DME": null,
  "DSI": null,
  "Daily FT": null,
  "Daily Mirror": null,
  "Danushka Gunathilaka": null,
  "Darcy": null,
  "Dasun Shanaka": null,
  "Data Protection": null,
  "David": null,
  "Deduru Oya": null,
  "Dehiwala Zoo": null,
  "Delta": null,
  "Demonstration Site": null,
  "Department of Commerce": null,
  "Derana": null,
  "Deshamanya": null,
  "Disha Patani": null,
  "Dombagoda": null,
  "Domestic Workers' Union": null,
  "Dotcom": null,
  "Dr G. Wijesuriya": null,
  "Dubai": null,
  "Duminda Silva": null,
  "Durham": null,
  "E&Y": null,
  "ECT": null,
  "Earth Networks Total Lightning Network Highest": null,
  "Easter": null,
  "Eastern": null,
  "Eastern Container Terminal": null,
  "Ed Klinger": null,
  "Education": null,
  "Elevation Capital": null,
  "Elle": null,
  "Elpitiya": null,
  "Emami Realty": null,
  "Emami Realty Ltd": null,
  "Emirates Airlines": null,
  "England": null,
  "Environment and Social Risk Assessment": null,
  "Equestrian Jumping Individual": null,
  "Ernst & Young": null,
  "Ethiopia": null,
  "European": null,
  "Evangeline": null,
  "Evergreen Group of Companies": null,
  "Expolanka Holdings PLC": null,
  "Ezmaline Zunaiha Jaro": null,
  "Fashinza": null,
  "Federation of Chambers of Commerce and Industry of Sri Lanka": null,
  "Finance": null,
  "Finance Ministry": null,
  "Finetech Consultancy": null,
  "Florence Singanayagam": null,
  "Florida": null,
  "Foreign Ministry": null,
  "Fort": null,
  "Fort Magistrate's": null,
  "France": null,
  "French": null,
  "G.L. Peiris": null,
  "Galadari Hotel, Colombo": null,
  "Galle": null,
  "Gampaha": null,
  "Gampaha Districts": null,
  "Gemini Ganesan": null,
  "General Trading Division": null,
  "Geneva": null,
  "Ghana": null,
  "Gibbs": null,
  "Glad": null,
  "Gotabaya Rajapaksa": null,
  "Gotabaya Rajapaksa Government": null,
  "Government": null,
  "Government Information Department": null,
  "Government of Japan": null,
  "Great Sober Island": null,
  "Gujarat": null,
  "Guwahati": null,
  "HISSL": null,
  "HSBC Sri Lanka": null,
  "Haliella": null,
  "Hardik Pandya": null,
  "Hasaranga": null,
  "Hayleys Advantis Group": null,
  "Heads of Churches": null,
  "Health": null,
  "Health Guidelines, Public Services": null,
  "Health Informatics Society of": null,
  "Health Ministry": null,
  "Herat": null,
  "Herath Mudiyanselage": null,
  "Herschelle Gibbs": null,
  "High Commission of India": null,
  "High Court": null,
  "High Courts": null,
  "Hindu": null,
  "Hindustan Times": null,
  "Hong Kong University Prof.": null,
  "Hospital": null,
  "Hotels Association of Sri Lanka": null,
  "Human Rights Commission": null,
  "Hyacinth Wijeratne": null,
  "Hyde Park": null,
  "ICC": null,
  "ICC Cricket World Cup Super League Standings": null,
  "IMF": null,
  "IMF Central Bank": null,
  "IPKF": null,
  "ITV Channel's": null,
  "ITV News Channel": null,
  "Ifham Nizam Senior": null,
  "Imran Khan's": null,
  "Inc.": null,
  "India": null,
  "India Air Force": null,
  "Indian": null,
  "Indian Air Force": null,
  "Indo Sri Lanka Accord": null,
  "Indo-Sri Lanka Peace Accord": null,
  "Indonesian": null,
  "Industrial, Nutrition and Construction Chemicals": null,
  "Industry Forum": null,
  "Information and Communication Agency": null,
  "Institute of Chartered Accountants of Sri Lanka": null,
  "International Chamber of Commerce Sri Lanka": null,
  "International Monetary Fund": null,
  "International Retail Bank of the year": null,
  "International Sovereign Bonds": null,
  "Iran": null,
  "Iranian": null,
  "Island Financial Review": null,
  "Israel": null,
  "Israeli": null,
  "Isuru": null,
  "Isuru Udana": null,
  "Italian": null,
  "Jaffna": null,
  "Jakarta": null,
  "Japan": null,
  "Japanese": null,
  "Jay Shah": null,
  "Joe Root": null,
  "John Kotelawala": null,
  "Joint Center": null,
  "Judicial Service Association": null,
  "Judicial Service Commission": null,
  "Justice": null,
  "K Gowtham": null,
  "KDU": null,
  "KPL": null,
  "Kalutara": null,
  "Kandy": null,
  "Kankasanturai": null,
  "Kashmir Premier League": null,
  "Kegalle": null,
  "Kerala": null,
  "King of Saudi Arabia": null,
  "Kiribathgoda": null,
  "Kithsiri De Mel": null,
  "Kolkata": null,
  "Kooratiyahena": null,
  "Korea": null,
  "Kotelawala Defence University": null,
  "Kotelawala National Defense University": null,
  "Kr": null,
  "Krunal Pandya": null,
  "Kumar Sangakkara's": null,
  "Kumu Kahua Theatre": null,
  "Kusal Mendis": null,
  "KusalMendis": null,
  "LOLC Holdings": null,
  "Labour Department": null,
  "Lady Ridgeway Children's Hospital": null,
  "Lady Ridgeway Hospital": null,
  "Lakvijaya Coal Power Plant": null,
  "Lalith U Gamage": null,
  "Lamont Jacobs": null,
  "Lamont Marcell Jacobs": null,
  "Lanka": null,
  "Lansakara": null,
  "Lekhwiya": null,
  "Lesley Bellew": null,
  "Liberation Army": null,
  "Lindula": null,
  "Lindula, Thalawakele": null,
  "London": null,
  "M.G. Ramachandran": null,
  "MD": null,
  "MEPA": null,
  "MGR": null,
  "MP Rishad Bathiudeen's": null,
  "Magistrates": null,
  "Maha Vihara": null,
  "Mahinda Rajapaksa": null,
  "Mahinda Yapa Abeywardana": null,
  "Mahinda Yapa Abeywardena": null,
  "Mail": null,
  "Maithripala Sirisena": null,
  "Makita": null,
  "Mala Chellappah": null,
  "Maldives": null,
  "Malik Peiris": null,
  "Mal\u00e9": null,
  "Mandaitivu Island": null,
  "Mandarin Reid": null,
  "Manoranjan Barman": null,
  "Marine Environment Protection Authority": null,
  "MasterCard": null,
  "Mattala": null,
  "May.": null,
  "Mechanical-Electrical-Plumbing": null,
  "Media Division": null,
  "Meeting": null,
  "Milinda Moragoda": null,
  "Ministry of Foreign Affairs": null,
  "Ministry of Health": null,
  "Ministry of Justice": null,
  "Ministry of Public Health": null,
  "Ministry of Tourism": null,
  "Money & Capital Market": null,
  "Money, Capital Markets and Public Enterprise Reforms Ajith Nivard": null,
  "Moragoda": null,
  "Moscow": null,
  "Motor Insurance": null,
  "Motor Plus": null,
  "Mumbai": null,
  "Muslim": null,
  "N Sathiya Moorthy Speculation": null,
  "NCC": null,
  "NIKE": null,
  "NSO Group": null,
  "Naftali Bennett": null,
  "Namal Rajapaksa": null,
  "Nanjing": null,
  "Narahenpita": null,
  "National Centre for Missing and Exploited Children": null,
  "National Christian Council of Sri Lanka": null,
  "National ICT, Telecommunications and Mobile Services Provider": null,
  "National Identity Cards": null,
  "National Operation Centre": null,
  "National Operations Centre for Prevention of COVID-19": null,
  "National Operations Centre for Prevention of COVID-19 - Get": null,
  "National Peoples' Power": null,
  "National Sports Week": null,
  "National Sustainable Destination Certification (NSDC": null,
  "National Sustainable Tourism Initiative": null,
  "Navajo Nation": null,
  "Navy": null,
  "Nayani": null,
  "Ned": null,
  "Nepal": null,
  "Nev.": null,
  "Nevada": null,
  "New Delhi": null,
  "New Zealand": null,
  "Nigeria": null,
  "Nikaweratiya": null,
  "Nimali Liyanarchchi": null,
  "Nimalsiri Edirisinghe": null,
  "Niroshan Dickwella": null,
  "Nisal Baduge": null,
  "Nishantha Ulugetenne": null,
  "Nitesh Kumar": null,
  "Norochcholai": null,
  "ODI": null,
  "Olympic": null,
  "Oman": null,
  "Osaka": null,
  "Overseas Warriors": null,
  "Oxford": null,
  "PTA": null,
  "Pakeer Amza": null,
  "Pakistan": null,
  "Pambahinna Junction": null,
  "Pan Asia Banking Corporation PLC": null,
  "Panagoda": null,
  "Panduka Karunanayake": null,
  "Pandya": null,
  "Paris": null,
  "Parliamentarian": null,
  "Passara": null,
  "Pathfinder Foundation": null,
  "Pavithra Wanniarachchi": null,
  "Pelawatte": null,
  "People's Bank": null,
  "People's Bank Chief Executive Officer": null,
  "Peradeniya Teaching Hospital": null,
  "Philippines": null,
  "Piramal Glass Ceylon PLC": null,
  "Police Special Task Force": null,
  "Pottuvil": null,
  "Presidential Commission of Inquiry": null,
  "Prevention of Terrorism Act": null,
  "Prince Faisal bin Abdulla Al Faisal Al Saud": null,
  "Prithvi": null,
  "Prithvi Shaw": null,
  "Proposal": null,
  "Provincial Councils and Local Government": null,
  "Public Health Inspectors": null,
  "Puttalam": null,
  "Qatar": null,
  "Qatar Airways": null,
  "R.": null,
  "R. Premadasa International Cricket Stadium": null,
  "ROCK": null,
  "Rajapaksa": null,
  "Rakwana": null,
  "Rani Reserve Forest": null,
  "Ranil Wickremasinghe": null,
  "Ranil Wickremesinghe": null,
  "Ranjith Kodituwakku": null,
  "Ratnapura": null,
  "Rear Admiral": null,
  "Registrar General's Department": null,
  "Republic of Maldives": null,
  "Residencies": null,
  "Retd": null,
  "Rishad Bathiudeen": null,
  "Rishad Bathiudeen's": null,
  "Rolex Watch Company": null,
  "Roman Catholic College": null,
  "Rosy Senanayake": null,
  "Rotary Club": null,
  "Rotary Club of Colombo": null,
  "Rotary Club of Colombo Fort": null,
  "Rotary Club of Colombo Tech City": null,
  "Royal College of Obstetricians and Gynaecologists": null,
  "Royal College of Surgeons": null,
  "Rtn": null,
  "Russel Arnold": null,
  "Russia": null,
  "Russian": null,
  "Ruwan Wijewardena": null,
  "Ruwan Wijewardene": null,
  "SJB": null,
  "SLC": null,
  "SLFP": null,
  "SLN": null,
  "SLSC": null,
  "SME": null,
  "Sabaragamuwa": null,
  "Sabaragamuwa Province": null,
  "Sajith Attygalle": null,
  "Sajith Premadasa": null,
  "Salt Lake City": null,
  "Sampath Bank PLC": null,
  "Sanath Nanayakkare Venora Group of Companies": null,
  "Santorini Resort Apartments": null,
  "Sarah Ward": null,
  "Sarath Weerasekara": null,
  "Sardinia": null,
  "Sasika Sadun Herath": null,
  "Secondary Public Offering": null,
  "Senegal": null,
  "Serum Institute of India": null,
  "Shane Warne": null,
  "Shanghai Hongqiao": null,
  "Shavendra Silva": null,
  "Shikhar Dhawan": null,
  "Sigiriya": null,
  "Singapore": null,
  "Sino": null,
  "Sinopharm": null,
  "Sinopharm Covid": null,
  "Sivaji Ganesan": null,
  "Sonam Kapoor Ahuja": null,
  "South Africa": null,
  "South African": null,
  "South Asian": null,
  "South Korea's": null,
  "Special Drawing Rights": null,
  "Spinner Wanindu Hasaranga": null,
  "Sri Jayewardenepura University's Immunology and Molecular Medicine Department": null,
  "Sri Lanka": null,
  "Sri Lanka Army": null,
  "Sri Lanka Army Cricket Committee": null,
  "Sri Lanka Army Dinesh": null,
  "Sri Lanka Army's": null,
  "Sri Lanka Cricket": null,
  "Sri Lanka Cricket Institute": null,
  "Sri Lanka Cricket's": null,
  "Sri Lanka Freedom Party": null,
  "Sri Lanka Insurance": null,
  "Sri Lanka Insurance Corporation": null,
  "Sri Lanka Insurance Motor": null,
  "Sri Lanka Insurance Motor Plus'": null,
  "Sri Lanka Navy": null,
  "Sri Lanka Ports Authority": null,
  "Sri Lanka Railway's": null,
  "Sri Lanka Sabaragamuwa University Lecturers' Association": null,
  "Sri Lanka Shipping Company": null,
  "Sri Lanka Veterinary Association": null,
  "Sri Lanka's": null,
  "Sri Lankan": null,
  "Sri Lankan Airlines": null,
  "Sri Lankans": null,
  "SriLanka": null,
  "SriLankan Airlines": null,
  "SriLankan Engineering": null,
  "Standard Chartered Sri Lanka": null,
  "State": null,
  "Steve Sisolak": null,
  "Supreme Court": null,
  "Suryakumar": null,
  "Swede Mathilda Karlsson": null,
  "Swiss": null,
  "Switzerland": null,
  "Syria": null,
  "Sysco": null,
  "Taliban": null,
  "Tamil": null,
  "Tamim": null,
  "Team India": null,
  "Tedros Adhanom": null,
  "Thivanki Madumali": null,
  "Thondamanaru": null,
  "Tiger Shroff": null,
  "Tigray": null,
  "Tokyo": null,
  "Torrington": null,
  "Tourism Development Authority": null,
  "Treasury": null,
  "Turkey": null,
  "Twitter": null,
  "U.N.": null,
  "U.S.": null,
  "UAE": null,
  "UB": null,
  "UK": null,
  "UN": null,
  "UNAMA": null,
  "UNDP": null,
  "UNESCO": null,
  "UNP": null,
  "US": null,
  "Udana": null,
  "Umaria Sinhawansa": null,
  "Union Bank Ltd": null,
  "Union Bank of Colombo PLC": null,
  "United Arab Emirates": null,
  "United Nations": null,
  "United Nations Assistance Mission": null,
  "United Nations Human Rights Council (UNHRC": null,
  "United States": null,
  "University of Hong Kong": null,
  "Upendra Pieris": null,
  "Urban Development Authority": null,
  "Uva": null,
  "Uyana": null,
  "Vallibel Finance PLC": null,
  "Veneto": null,
  "Venora Group": null,
  "Vera Gamini Samarasinghe": null,
  "Vihara Maha Devi Park": null,
  "Viharamahadevi Park": null,
  "Vijitha Herath": null,
  "Visa": null,
  "Vistas of Splendour": null,
  "Vyshnavy": null,
  "W.D. Lakshman": null,
  "WHO": null,
  "Wanindu Hasarang": null,
  "Wathurawila Tea Factory": null,
  "Welikada Police": null,
  "West Africa": null,
  "Wijewardene": null,
  "World Health - Get": null,
  "World Health Orgainsation": null,
  "World Health Organisation": null,
  "World Health Organization": null,
  "World Health Organization Country Office": null,
  "World Youth Skills Day'": null,
  "Wuhan": null,
  "Xi Jinping": null,
  "Yemen": null,
  "Yorkshire": null,
  "Yoshihide Suga": null,
  "Yupun Abeykoon's": null,
  "Yuzvendra Chahal": null,
  "Zhangjiajie": null,
  "Zoom Video Communication Inc.'s": null,
  "Zurich": null,
  "all-American": null,
  "anti-Tamil": null,
  "bin Hamad Al Thani": null,
  "bowler": null,
  "g1": null,
  "www.airports.com.mv": null
}
